README
setup.cfg
setup.py
Cambiatuscromos.egg-info/PKG-INFO
Cambiatuscromos.egg-info/SOURCES.txt
Cambiatuscromos.egg-info/dependency_links.txt
Cambiatuscromos.egg-info/entry_points.txt
Cambiatuscromos.egg-info/not-zip-safe
Cambiatuscromos.egg-info/requires.txt
Cambiatuscromos.egg-info/top_level.txt
cambiatuscromos/__init__.py
cambiatuscromos/cromos.py