Metadata-Version: 1.0
Name: Cambiatuscromos
Version: 0.1.1alpha
Summary: Chequeo automatico de intercambios para Cambiatuscromos.org
Home-page: UNKNOWN
Author: Miguel Sempere
Author-email: odoncopon@gmail.com
License: GPLv3
Keywords: checker chequeo automatico cambiatuscromos cromos cambiar intercambios panini
Platform: UNKNOWN
Classifier: Development Status :: 3 - Alpha
Classifier: Programming Language :: Python
Classifier: Environment :: Console
Classifier: Topic :: Utilities
Classifier: Topic :: Internet :: WWW/HTTP
Classifier: License :: OSI Approved :: GNU General Public License v3 (GPLv3)
